pepp/__init__.py
pepp/cli.py
pepp/core.py
pepp/test.py
pepp-0.0.1.dist-info/METADATA
pepp-0.0.1.dist-info/RECORD
pepp-0.0.1.dist-info/WHEEL
pepp-0.0.1.dist-info/top_level.txt
